Metadata-Version: 1.0
Name: jag-distributions
Version: 0.1
Summary: Gaussian & Binomial distributions
Home-page: UNKNOWN
Author: Jeroen Goddijn
Author-email: UNKNOWN
License: UNKNOWN
Platform: UNKNOWN
